ingest_utils/__init__.py
ingest_utils/decorators.py
ingest_utils/pklr.py
ingest_utils/dist/tmpaolhkjxk.whl
ingest_utils-0.0.6.dist-info/WHEEL
ingest_utils-0.0.6.dist-info/METADATA
ingest_utils-0.0.6.dist-info/RECORD
