Metadata-Version: 1.2
Name: ingest_utils
Version: 0.0.6
Summary: A few utils for operations common to ingestion tasks 
Home-page: http://github.com/n2itn
License: UNKNOWN
Author: Zach@livestories.com
Author-email: Zach@livestories.com
Classifier: License :: OSI Approved :: Apache Software License
